<?xml version="1.0" encoding="UTF-8" standalone="yes"?>
<Order>
  <OrderId>4035</OrderId>
  <OrderTime>10:51:05</OrderTime>
  <OrderDate>2020-09-09</OrderDate>
  <ShippingFullName>jane rogin nilsson</ShippingFullName>
  <ShippingAddress1>Banérgatan 21</ShippingAddress1>
  <ShippingAddress2/>
  <ShippingCity>Stockholm</ShippingCity>
  <ShippingPostcode>11522</ShippingPostcode>
  <OrderLineItems>
    <OrderLineItem>
      <Id>865</Id>
      <Name>Auberginelasagne</Name>
      <ProductId>2847</ProductId>
      <SKU>419IT9012817</SKU>
      <Quantity>2</Quantity>
      <Price>65</Price>
      <Subtotal>130</Subtotal>
      <SubtotalTax>0</SubtotalTax>
      <Total>130</Total>
      <TotalTax>0</TotalTax>
    </OrderLineItem>
  </OrderLineItems>
  <ShipmentNumber>UNI1001246103</ShipmentNumber>
</Order>
